[
  {
    "id": 107,
    "title": "스퀘어넥 패턴 블라우스",
    "filter": "top",
    "price": 219000,
    "count": 1,
    "url": "https://alwayz0121.github.io/thursday_island_json/img/top/top107.jpg"
  },
  {
    "id": 108,
    "title": "프릴 핀턱 볼륨 블라우스",
    "filter": "top",
    "price": 125300,
    "count": 1,
    "url": "https://alwayz0121.github.io/thursday_island_json/img/top/top108.jpg"
  },
  {
    "id": 109,
    "title": "레이스 블라우스",
    "filter": "top",
    "price": 199000,
    "count": 1,
    "url": "https://alwayz0121.github.io/thursday_island_json/img/top/top109.jpg"
  }
]
